impc_api_helper/__init__.py
impc_api_helper/facet_request.py
impc_api_helper/iterator_solr_request.py
impc_api_helper/solr_request.py
impc_api_helper-0.1.0.dist-info/LICENSE
impc_api_helper-0.1.0.dist-info/METADATA
impc_api_helper-0.1.0.dist-info/WHEEL
impc_api_helper-0.1.0.dist-info/top_level.txt
impc_api_helper-0.1.0.dist-info/RECORD
