Metadata-Version: 2.1
Name: impc-_api_helper
Version: 0.1.0
Summary: A package to facilitate making API requests to the IMPC Solr API
Home-page: https://github.com/marinak-ebi/impc-workshop
Author: MPI2, Marina Kan, Diego Pava
Project-URL: Homepage, https://github.com/marinak-ebi/impc-workshop
Requires-Python: >=3.10
License-File: LICENSE
Requires-Dist: pandas >=2.2.0
Requires-Dist: requests >=2.31.0
Requires-Dist: tqdm >=4.66.4
